pyocd/__init__.py
pyocd/__main__.py
pyocd/_version.py
pyocd/board/__init__.py
pyocd/board/board.py
pyocd/board/board_ids.py
pyocd/board/mbed_board.py
pyocd/cache/__init__.py
pyocd/cache/memory.py
pyocd/cache/metrics.py
pyocd/cache/register.py
pyocd/commands/__init__.py
pyocd/commands/base.py
pyocd/commands/commander.py
pyocd/commands/commands.py
pyocd/commands/execution_context.py
pyocd/commands/repl.py
pyocd/commands/values.py
pyocd/core/__init__.py
pyocd/core/core_registers.py
pyocd/core/core_target.py
pyocd/core/exceptions.py
pyocd/core/helpers.py
pyocd/core/memory_interface.py
pyocd/core/memory_map.py
pyocd/core/options.py
pyocd/core/options_manager.py
pyocd/core/plugin.py
pyocd/core/session.py
pyocd/core/soc_target.py
pyocd/core/target.py
pyocd/core/target_delegate.py
pyocd/coresight/__init__.py
pyocd/coresight/ap.py
pyocd/coresight/component.py
pyocd/coresight/component_ids.py
pyocd/coresight/core_ids.py
pyocd/coresight/coresight_target.py
pyocd/coresight/cortex_m.py
pyocd/coresight/cortex_m_core_registers.py
pyocd/coresight/cortex_m_v8m.py
pyocd/coresight/dap.py
pyocd/coresight/discovery.py
pyocd/coresight/dwt.py
pyocd/coresight/fpb.py
pyocd/coresight/funnel.py
pyocd/coresight/generic_mem_ap.py
pyocd/coresight/gpr.py
pyocd/coresight/itm.py
pyocd/coresight/minimal_mem_ap.py
pyocd/coresight/rom_table.py
pyocd/coresight/sdc600.py
pyocd/coresight/tpiu.py
pyocd/debug/__init__.py
pyocd/debug/cache.py
pyocd/debug/context.py
pyocd/debug/rtt.py
pyocd/debug/semihost.py
pyocd/debug/symbols.py
pyocd/debug/breakpoints/__init__.py
pyocd/debug/breakpoints/manager.py
pyocd/debug/breakpoints/provider.py
pyocd/debug/breakpoints/software.py
pyocd/debug/elf/__init__.py
pyocd/debug/elf/decoder.py
pyocd/debug/elf/elf.py
pyocd/debug/elf/elf_reader.py
pyocd/debug/elf/symbols.py
pyocd/debug/sequences/__init__.py
pyocd/debug/sequences/delegates.py
pyocd/debug/sequences/functions.py
pyocd/debug/sequences/scope.py
pyocd/debug/sequences/sequences.lark
pyocd/debug/sequences/sequences.py
pyocd_faultier-0.36.1.dev15.dist-info/licenses/LICENSE
pyocd_faultier-0.36.1.dev15.dist-info/METADATA
pyocd_faultier-0.36.1.dev15.dist-info/WHEEL
pyocd_faultier-0.36.1.dev15.dist-info/entry_points.txt
pyocd_faultier-0.36.1.dev15.dist-info/top_level.txt
pyocd_faultier-0.36.1.dev15.dist-info/zip-safe
pyocd_faultier-0.36.1.dev15.dist-info/RECORD
