Metadata-Version: 2.4
Name: pyocd-faultier
Version: 0.36.1.dev15
Summary: Cortex-M debugger for Python
Home-page: https://github.com/hextree/pyOCD
Maintainer: Chris Reed
Maintainer-email: chris.reed@arm.com
License: Apache 2.0
Project-URL: Website, https://pyocd.io/
Project-URL: Documentation, https://pyocd.io//docs
Project-URL: Source, https://github.com/pyocd/pyOCD
Project-URL: Issues, https://github.com/pyocd/pyOCD/issues
Project-URL: Discussions, https://github.com/pyocd/pyOCD/discussions
Project-URL: Releases, https://github.com/pyocd/pyOCD/releases
Keywords: embedded,debug,debugger,arm,gdb,gdbserver,flash,test
Classifier: Development Status :: 5 - Production/Stable
Classifier: Environment :: Console
Classifier: Intended Audience :: Developers
Classifier: Intended Audience :: Manufacturing
Classifier: Intended Audience :: Science/Research
Classifier: License :: OSI Approved :: Apache Software License
Classifier: Operating System :: MacOS :: MacOS X
Classifier: Operating System :: Microsoft :: Windows
Classifier: Operating System :: POSIX
Classifier: Operating System :: POSIX :: BSD
Classifier: Operating System :: POSIX :: Linux
Classifier: Programming Language :: Python
Classifier: Programming Language :: Python :: 3
Classifier: Programming Language :: Python :: 3.7
Classifier: Programming Language :: Python :: 3.8
Classifier: Programming Language :: Python :: 3.9
Classifier: Programming Language :: Python :: 3.10
Classifier: Programming Language :: Python :: 3.11
Classifier: Topic :: Software Development
Classifier: Topic :: Software Development :: Debuggers
Classifier: Topic :: Software Development :: Embedded Systems
Classifier: Topic :: Software Development :: Testing
Classifier: Topic :: Utilities
Requires-Python: >=3.7.0
License-File: LICENSE
Requires-Dist: capstone<5.0,>=4.0
Requires-Dist: cmsis-pack-manager<1.0,>=0.5.2
Requires-Dist: colorama<1.0
Requires-Dist: hidapi<1.0,>=0.10.1; platform_system != "Linux"
Requires-Dist: importlib_metadata>=3.6
Requires-Dist: importlib_resources
Requires-Dist: intelhex<3.0,>=2.0
Requires-Dist: intervaltree<4.0,>=3.0.2
Requires-Dist: lark<2.0,>=1.1.5
Requires-Dist: libusb-package<2.0,>=1.0
Requires-Dist: natsort<9.0,>=8.0.0
Requires-Dist: prettytable<4.0,>=2.0
Requires-Dist: pyelftools<1.0
Requires-Dist: pylink-square<2.0,>=1.0
Requires-Dist: pyusb<2.0,>=1.2.1
Requires-Dist: pyyaml<7.0,>=6.0
Requires-Dist: six<2.0,>=1.15.0
Requires-Dist: typing-extensions<5.0,>=4.0
Provides-Extra: pemicro
Requires-Dist: pyocd_pemicro>=1.0.6; extra == "pemicro"
Provides-Extra: test
Requires-Dist: pytest>=6.2; extra == "test"
Requires-Dist: pytest-cov; extra == "test"
Requires-Dist: coverage; extra == "test"
Requires-Dist: flake8; extra == "test"
Requires-Dist: pylint; extra == "test"
Requires-Dist: tox; extra == "test"
Dynamic: license-file
